ghstats/__init__.py
ghstats/__main__.py
ghstats/ghstats.py
ghstats-2.0.0.dist-info/LICENSE
ghstats-2.0.0.dist-info/METADATA
ghstats-2.0.0.dist-info/WHEEL
ghstats-2.0.0.dist-info/entry_points.txt
ghstats-2.0.0.dist-info/top_level.txt
ghstats-2.0.0.dist-info/RECORD
