Metadata-Version: 2.1
Name: ghstats
Version: 2.0.0
Summary: GitHub Release download count and other statistics.
Home-page: https://github.com/kefir500/ghstats
Author: Alexander Gorishnyak
Author-email: kefir500@gmail.com
License: MIT
Keywords: github release download count stats statistics
Platform: UNKNOWN
Classifier: Development Status :: 5 - Production/Stable
Classifier: Environment :: Console
Classifier: Intended Audience :: Developers
Classifier: License :: OSI Approved :: MIT License
Classifier: Natural Language :: English
Classifier: Operating System :: OS Independent
Classifier: Programming Language :: Python :: 3
Classifier: Topic :: Utilities
Requires-Python: >=3
License-File: LICENSE
